[
  {
    "name": "Cheese",
    "brand": "Cheesedale",
    "supermarket": "Village Grocer",
    "price": 7.7,
    "category": "dairy",
    "date": "2025-08-07"
  },
  {
    "name": "Wagyu Burger",
    "brand": "Village Grocer",
    "supermarket": "Village Grocer",
    "price": 10.9,
    "category": "uncategorized",
    "date": "2025-08-07"
  },
  {
    "name": "Burger Buns (4)",
    "brand": "Village Grocer",
    "supermarket": "Village Grocer",
    "price": 5,
    "category": "bakery",
    "date": "2025-08-07"
  },
  {
    "name": "UHT Full Cream Milk",
    "brand": "Goodday",
    "supermarket": "Village Grocer",
    "price": 8.5,
    "category": "dairy",
    "date": "2025-08-07"
  },
  {
    "name": "Dishwashing Liquid",
    "brand": "Biohome",
    "supermarket": "Village Grocer",
    "price": 12.9,
    "category": "household",
    "date": "2025-08-07"
  },
  {
    "name": "Enoki Mushrooms",
    "brand": "Village Grocer",
    "supermarket": "Village Grocer",
    "price": 1.05,
    "category": "uncategorized",
    "date": "2025-08-07"
  },
  {
    "name": "Enoki Mushrooms",
    "brand": "Lotus",
    "supermarket": "Lotus",
    "price": 0.95,
    "category": "uncategorized",
    "date": "2025-08-07"
  },
  {
    "name": "Sweetened Creamer",
    "brand": "Saji",
    "supermarket": "Village Grocer",
    "price": 3.5,
    "category": "dairy",
    "date": "2025-08-08",
    "priceHistory": [
      {
        "price": 3.75,
        "date": "2025-08-08"
      },
      {
        "price": 3.5,
        "date": "2025-08-08"
      }
    ]
  },
  {
    "name": "Sweetened Creamer",
    "brand": "Saji",
    "supermarket": "99 Speedmart",
    "price": 3.25,
    "category": "dairy",
    "date": "2025-08-08",
    "priceHistory": [
      {
        "price": 3.75,
        "date": "2025-08-08"
      },
      {
        "price": 3.25,
        "date": "2025-08-08"
      }
    ]
  },
  {
    "name": "All Purpose Flour",
    "brand": "Cap Sauh",
    "supermarket": "Village Grocer",
    "price": 3.9,
    "category": "uncategorized",
    "date": "2025-08-13",
    "priceHistory": [
      {
        "price": 3.2,
        "date": "2025-08-08"
      },
      {
        "price": 3.25,
        "date": "2025-08-08"
      }
    ]
  },
  {
    "name": "All Purpose Flour",
    "brand": "Cap Sauh",
    "supermarket": "99 Speedmart",
    "price": 2.9,
    "category": "uncategorized",
    "date": "2025-08-08"
  },
  {
    "name": "Macaroni",
    "brand": "Balducci",
    "supermarket": "Village Grocer",
    "price": 3.4,
    "category": "uncategorized",
    "date": "2025-08-08"
  },
  {
    "name": "Baking Soda",
    "brand": "Meriah",
    "supermarket": "Lotus",
    "price": 5.2,
    "category": "beverages",
    "date": "2025-08-08"
  },
  {
    "name": "MSG",
    "brand": "Ajinomoto",
    "supermarket": "Lotus",
    "price": 2.7,
    "category": "uncategorized",
    "date": "2025-08-08"
  },
  {
    "name": "Double Stuff Oreo",
    "brand": "Oreo",
    "supermarket": "Lotus",
    "price": 2.49,
    "category": "uncategorized",
    "date": "2025-08-08"
  },
  {
    "name": "Earl Grey Tea",
    "brand": "Ahmad Tea",
    "supermarket": "Lotus",
    "price": 5.99,
    "category": "beverages",
    "date": "2025-08-08"
  },
  {
    "name": "Kaya",
    "brand": "Auntie Ros Gardenia",
    "supermarket": "Lotus",
    "price": 3.9,
    "category": "uncategorized",
    "date": "2025-08-08"
  },
  {
    "name": "Apple Juice",
    "brand": "Marigold",
    "supermarket": "Lotus",
    "price": 3.5,
    "category": "produce",
    "date": "2025-08-08"
  },
  {
    "name": "Shiitake Mushroom",
    "brand": "Fungo",
    "supermarket": "Lotus",
    "price": 5.29,
    "category": "produce",
    "date": "2025-08-08"
  },
  {
    "name": "Sweetened Creamer",
    "brand": "F&N",
    "supermarket": "Lotus",
    "price": 3.69,
    "category": "dairy",
    "date": "2025-08-08"
  },
  {
    "name": "Beef Mince",
    "brand": "GF",
    "supermarket": "Lotus",
    "price": 12.49,
    "category": "meat",
    "date": "2025-08-08"
  },
  {
    "name": "Red Cherry Tomatoes",
    "brand": "Genting Garden",
    "supermarket": "Village Grocer",
    "price": 6.5,
    "category": "produce",
    "date": "2025-08-08"
  },
  {
    "name": "Cornstarch",
    "brand": "Cap Bintang",
    "supermarket": "Village Grocer",
    "price": 2.3,
    "category": "uncategorized",
    "date": "2025-08-13",
    "priceHistory": [
      {
        "price": 3,
        "date": "2025-08-09"
      },
      {
        "price": 2.3,
        "date": "2024-10-07"
      }
    ]
  },
  {
    "name": "Mayonnaise 310mL",
    "brand": "Kewpie",
    "supermarket": "Giant",
    "price": 11,
    "category": "condiments",
    "date": "2025-08-08"
  },
  {
    "name": "Mayonnaise 310mL",
    "brand": "Kewpie",
    "supermarket": "Village Grocer",
    "price": 11.35,
    "category": "condiments",
    "date": "2025-08-08"
  },
  {
    "name": "UHT Full Cream Milk",
    "brand": "Yarra",
    "supermarket": "99 Speedmart",
    "price": 5.99,
    "category": "dairy",
    "date": "2025-08-08"
  },
  {
    "name": "UHT Full Cream Milk",
    "brand": "Yarra",
    "supermarket": "Giant",
    "price": 5.29,
    "category": "dairy",
    "date": "2025-08-08"
  },
  {
    "name": "Vitagen Yogurt Drink",
    "brand": "Vitagen",
    "supermarket": "Village Grocer",
    "price": 10.65,
    "category": "dairy",
    "date": "2025-08-08"
  },
  {
    "name": "Santan UHT",
    "brand": "M&S",
    "supermarket": "Village Grocer",
    "price": 6.55,
    "category": "uncategorized",
    "date": "2025-08-08"
  },
  {
    "name": "Pure Olive Oil 750mL",
    "brand": "Naturel",
    "supermarket": "Village Grocer",
    "price": 53.5,
    "category": "uncategorized",
    "date": "2025-08-08"
  },
  {
    "name": "Pure Olive Oil 750mL",
    "brand": "Naturel",
    "supermarket": "Giant",
    "price": 53.3,
    "category": "uncategorized",
    "date": "2025-08-08"
  },
  {
    "name": "Pure Olive Oil 750mL",
    "brand": "Naturel",
    "supermarket": "99 Speedmart",
    "price": 33.5,
    "category": "uncategorized",
    "date": "2025-08-08"
  },
  {
    "name": "Apple Juice",
    "brand": "Marigold",
    "supermarket": "Village Grocer",
    "price": 3.6,
    "category": "produce",
    "date": "2025-08-08"
  },
  {
    "name": "UHT Full Cream Milk",
    "brand": "Dutch Lady",
    "supermarket": "Village Grocer",
    "price": 7.9,
    "category": "dairy",
    "date": "2025-08-08"
  },
  {
    "name": "Canola Oil 1L",
    "brand": "Naturel",
    "supermarket": "Village Grocer",
    "price": 14.7,
    "category": "uncategorized",
    "date": "2025-08-08"
  },
  {
    "name": "Maggi Kari 5x79g",
    "brand": "Maggi",
    "supermarket": "Village Grocer",
    "price": 4.95,
    "category": "uncategorized",
    "date": "2022-02-20",
    "priceHistory": [
      {
        "price": 6.25,
        "date": "2025-08-08"
      }
    ]
  },
  {
    "name": "Eggs x30",
    "brand": "Savoir Grade A",
    "supermarket": "Village Grocer",
    "price": 12.6,
    "category": "uncategorized",
    "date": "2025-08-08"
  },
  {
    "name": "Caesar Salad",
    "brand": "Genting Garden",
    "supermarket": "Village Grocer",
    "price": 8,
    "category": "uncategorized",
    "date": "2025-08-08"
  },
  {
    "name": "Maggi Ayam",
    "brand": "Maggi",
    "supermarket": "Village Grocer",
    "price": 6.25,
    "category": "uncategorized",
    "date": "2025-08-08"
  },
  {
    "name": "Red Chillies per kg",
    "brand": "Per kg",
    "supermarket": "Village Grocer",
    "price": 15.29,
    "category": "uncategorized",
    "date": "2024-09-15"
  },
  {
    "name": "Canola Oil 1L",
    "brand": "Naturel",
    "supermarket": "Giant",
    "price": 14.7,
    "category": "uncategorized",
    "date": "2025-08-08"
  },
  {
    "name": "Hup Seng Cream Crackers",
    "brand": "Hup Seng",
    "supermarket": "Lotus",
    "price": 4.49,
    "category": "dairy",
    "date": "2025-08-08"
  },
  {
    "name": "Vanilla Flavouring",
    "brand": "Star Brand",
    "supermarket": "Lotus",
    "price": 2.6,
    "category": "uncategorized",
    "date": "2025-08-08"
  },
  {
    "name": "Oreo 3x9",
    "brand": "Oreo 3pcs x 9 packs",
    "supermarket": "Lotus",
    "price": 5.69,
    "category": "uncategorized",
    "date": "2025-08-08"
  },
  {
    "name": "Potato Chips",
    "brand": "The Golden Duck - Truffle Wagyu",
    "supermarket": "Village Grocer",
    "price": 8.9,
    "category": "produce",
    "date": "2025-08-08"
  },
  {
    "name": "Instant Mi Goreng",
    "brand": "Indomie x10",
    "supermarket": "Village Grocer",
    "price": 10.69,
    "category": "uncategorized",
    "date": "2025-08-08"
  },
  {
    "name": "Pepsi Black 1.5L",
    "brand": "Pepsi",
    "supermarket": "Village Grocer",
    "price": 4.7,
    "category": "uncategorized",
    "date": "2025-08-08"
  },
  {
    "name": "Yellow Onion",
    "brand": "Per kg",
    "supermarket": "Village Grocer",
    "price": 3.9,
    "category": "produce",
    "date": "2025-08-08"
  },
  {
    "name": "Red Chillies per kg",
    "brand": "Per kg",
    "supermarket": "Village Grocer",
    "price": 15.29,
    "category": "uncategorized",
    "date": "2024-09-15",
    "priceHistory": [
      {
        "price": 0.352,
        "date": "2025-08-08"
      }
    ]
  },
  {
    "name": "Pepsi Black 1.5L",
    "brand": "Pepsi",
    "supermarket": "Adam Mini Mart",
    "price": 5.5,
    "category": "uncategorized",
    "date": "2025-08-13",
    "priceHistory": [
      {
        "price": 4.9,
        "date": "2025-08-08"
      }
    ]
  },
  {
    "name": "Red Chillies per kg",
    "brand": "Per kg",
    "supermarket": "Village Grocer",
    "price": 15.29,
    "category": "uncategorized",
    "date": "2024-09-15",
    "priceHistory": [
      {
        "price": 0.352,
        "date": "2025-08-08"
      }
    ]
  },
  {
    "name": "Test Items",
    "brand": "Testing2",
    "supermarket": "Jaya Grocer",
    "price": 1.29,
    "category": "uncategorized",
    "date": "2025-08-13",
    "priceHistory": [
      {
        "price": 29.99,
        "date": "2025-08-09"
      },
      {
        "price": 69.99,
        "date": "2025-08-09"
      },
      {
        "price": 60.69,
        "date": "2025-08-09"
      },
      {
        "price": 67.67,
        "date": "2025-08-09"
      },
      {
        "price": 29.99,
        "date": "2025-08-09"
      },
      {
        "price": 69.99,
        "date": "2025-08-08"
      },
      {
        "price": 71.99,
        "date": "2025-08-08"
      },
      {
        "price": 72.99,
        "date": "2025-08-08"
      },
      {
        "price": 70.99,
        "date": "2024-11-15"
      },
      {
        "price": 60.96,
        "date": "2023-07-18"
      }
    ]
  },
  {
    "name": "Mayonnaise 310mL",
    "brand": "Kewpie",
    "supermarket": "Lotus",
    "price": 10.99,
    "category": "condiments",
    "date": "2025-08-08"
  },
  {
    "name": "Lime (Big)",
    "brand": "Per kg",
    "supermarket": "Village Grocer",
    "price": 9.4,
    "category": "produce",
    "date": "2025-08-08"
  },
  {
    "name": "Holland Potatoes",
    "brand": "Per kg",
    "supermarket": "Village Grocer",
    "price": 3.5,
    "category": "produce",
    "date": "2025-08-08"
  },
  {
    "name": "Spring Onions",
    "brand": "Per kg",
    "supermarket": "Village Grocer",
    "price": 16.05,
    "category": "produce",
    "date": "2025-08-08"
  },
  {
    "name": "UHT Full Cream Milk",
    "brand": "Dutch Lady",
    "supermarket": "99 Speedmart",
    "price": 6.4,
    "category": "dairy",
    "date": "2025-08-08"
  },
  {
    "name": "Maggi Kari 5x79g",
    "brand": "Maggi",
    "supermarket": "99 Speedmart",
    "price": 5.2,
    "category": "uncategorized",
    "date": "2025-08-08"
  },
  {
    "name": "Sugar 1kg",
    "brand": "CSR",
    "supermarket": "99 Speedmart",
    "price": 2.85,
    "category": "uncategorized",
    "date": "2024-10-20",
    "priceHistory": [
      {
        "price": 2.95,
        "date": "2025-08-08"
      }
    ]
  },
  {
    "name": "Indomie Mi Goreng Spesial x5",
    "brand": "Indomie",
    "supermarket": "99 Speedmart",
    "price": 4.9,
    "category": "uncategorized",
    "date": "2025-08-08"
  },
  {
    "name": "UHT Full Cream Milk",
    "brand": "Dutch Lady",
    "supermarket": "Kapitan Grocer JB",
    "price": 8.5,
    "category": "dairy",
    "date": "2025-08-08"
  },
  {
    "name": "Eggs x30",
    "brand": "Savoir Grade C",
    "supermarket": "Village Grocer",
    "price": 11.4,
    "category": "uncategorized",
    "date": "2025-08-08"
  },
  {
    "name": "Lemon",
    "brand": "Per pc",
    "supermarket": "Giant",
    "price": 2,
    "category": "produce",
    "date": "2025-08-08"
  },
  {
    "name": "Enoki Mushrooms",
    "brand": "Giant",
    "supermarket": "Giant",
    "price": 1.98,
    "category": "uncategorized",
    "date": "2024-10-02"
  },
  {
    "name": "Vanilla Flavouring",
    "brand": "Star Brand",
    "supermarket": "Giant",
    "price": 2.95,
    "category": "uncategorized",
    "date": "2024-10-02"
  },
  {
    "name": "White Vinegar 325mL",
    "brand": "Jalen",
    "supermarket": "Giant",
    "price": 2.6,
    "category": "condiments",
    "date": "2025-08-08"
  },
  {
    "name": "Broccoli China",
    "brand": "Per pc",
    "supermarket": "Giant",
    "price": 4.29,
    "category": "produce",
    "date": "2025-08-08"
  },
  {
    "name": "Valencia Navel Orange",
    "brand": "Per pc",
    "supermarket": "Giant",
    "price": 3,
    "category": "uncategorized",
    "date": "2025-08-08"
  },
  {
    "name": "Udon Noodles",
    "brand": "Vit’s 200gx3",
    "supermarket": "Giant",
    "price": 6.2,
    "category": "grainspastanoodles",
    "date": "2025-08-08"
  },
  {
    "name": "Eggs x30",
    "brand": "Savoir Grade B",
    "supermarket": "Village Grocer",
    "price": 12,
    "category": "uncategorized",
    "date": "2024-10-07"
  },
  {
    "name": "Cili Padi Merah",
    "brand": "Per kg",
    "supermarket": "Village Grocer",
    "price": 33.95,
    "category": "uncategorized",
    "date": "2025-08-08"
  },
  {
    "name": "Coriander",
    "brand": "Per kg",
    "supermarket": "Village Grocer",
    "price": 19.99,
    "category": "uncategorized",
    "date": "2025-08-08"
  },
  {
    "name": "Eggs x30",
    "brand": "QL Deli Grade C",
    "supermarket": "99 Speedmart",
    "price": 11.4,
    "category": "uncategorized",
    "date": "2024-10-20"
  },
  {
    "name": "Broccoli China",
    "brand": "Per pc",
    "supermarket": "Village Grocer",
    "price": 3.29,
    "category": "produce",
    "date": "2025-08-08"
  },
  {
    "name": "Instant Mi Goreng",
    "brand": "Indomie x5",
    "supermarket": "99 Speedmart",
    "price": 4.9,
    "category": "uncategorized",
    "date": "2025-08-08"
  },
  {
    "name": "Shallot",
    "brand": "Per kg",
    "supermarket": "Village Grocer",
    "price": 2.99,
    "category": "uncategorized",
    "date": "2025-08-08"
  },
  {
    "name": "Russet Potato",
    "brand": "Per kg",
    "supermarket": "Village Grocer",
    "price": 7.6,
    "category": "produce",
    "date": "2025-08-08"
  },
  {
    "name": "Sugar 1kg",
    "brand": "CSR",
    "supermarket": "Village Grocer",
    "price": 2.85,
    "category": "uncategorized",
    "date": "2020-10-05"
  },
  {
    "name": "Japanese Bread Flour 1kg",
    "brand": "Meriah",
    "supermarket": "Village Grocer",
    "price": 10.6,
    "category": "bakery",
    "date": "2025-08-08"
  },
  {
    "name": "Cornstarch",
    "brand": "Cap Bintang",
    "supermarket": "99 Speedmart",
    "price": 1.75,
    "category": "uncategorized",
    "date": "2025-08-09"
  },
  {
    "name": "Test Items",
    "brand": "Testing2",
    "supermarket": "Jaya Grocer",
    "price": 1.29,
    "category": "uncategorized",
    "date": "2025-08-13",
    "priceHistory": [
      {
        "price": 29.99,
        "date": "2025-08-09"
      },
      {
        "price": 69.99,
        "date": "2025-08-09"
      },
      {
        "price": 60.69,
        "date": "2025-08-09"
      },
      {
        "price": 67.67,
        "date": "2025-08-09"
      },
      {
        "price": 29.99,
        "date": "2025-08-09"
      },
      {
        "price": 69.99,
        "date": "2025-08-08"
      },
      {
        "price": 71.99,
        "date": "2025-08-08"
      },
      {
        "price": 72.99,
        "date": "2025-08-08"
      },
      {
        "price": 70.99,
        "date": "2024-11-15"
      },
      {
        "price": 60.96,
        "date": "2023-07-18"
      }
    ]
  },
  {
    "name": "Broccoli China",
    "brand": "Per pc",
    "supermarket": "Lotus",
    "price": 2.29,
    "category": "produce",
    "date": "2025-08-09"
  },
  {
    "name": "Command Strips Picture Hanging Medium",
    "brand": "Command Brand",
    "supermarket": "Jaya Grocer",
    "price": 18.4,
    "category": "uncategorized",
    "date": "2025-08-09"
  },
  {
    "name": "Chilli Flakes",
    "brand": "Mewah",
    "supermarket": "Village Grocer",
    "price": 6.9,
    "date": "2020-10-05",
    "category": "uncategorized"
  },
  {
    "name": "Shiitake Mushroom",
    "brand": "Fungo",
    "supermarket": "Village Grocer",
    "price": 4.9,
    "category": "produce",
    "date": "2020-10-05"
  },
  {
    "name": "Isotonic Drink",
    "brand": "Pocari Sweat 300mL",
    "supermarket": "Village Grocer",
    "price": 3,
    "date": "2020-10-05",
    "category": "beverages"
  },
  {
    "name": "Samyang Carbonara",
    "brand": "Samyang",
    "supermarket": "Village Grocer",
    "price": 21.9,
    "date": "2020-10-05",
    "category": "uncategorized"
  },
  {
    "name": "Mineral Water",
    "brand": "Spritzer 1.5L",
    "supermarket": "Village Grocer",
    "price": 2.19,
    "date": "2020-10-05",
    "category": "uncategorized"
  },
  {
    "name": "H&E Mango Chamomile",
    "brand": "Heaven and Earth 1.5L",
    "supermarket": "Village Grocer",
    "price": 5.2,
    "date": "2020-10-05",
    "category": "meat"
  },
  {
    "name": "Baking Soda",
    "brand": "Arm and Hammer 454g",
    "supermarket": "Village Grocer",
    "price": 7.55,
    "category": "beverages",
    "date": "2025-08-09"
  },
  {
    "name": "Tomatoes",
    "brand": "Vine Ripened per kg",
    "supermarket": "Village Grocer",
    "price": 14.2,
    "date": "2022-01-04",
    "category": "produce"
  },
  {
    "name": "White Garlic",
    "brand": "Per kg",
    "supermarket": "Village Grocer",
    "price": 11.5,
    "date": "2022-01-04",
    "category": "produce"
  },
  {
    "name": "Cornstarch",
    "brand": "Star Brand",
    "supermarket": "Lotus",
    "price": 1.7,
    "category": "uncategorized",
    "date": "2025-08-09"
  },
  {
    "name": "Kway Teow Noodles",
    "brand": "UG",
    "supermarket": "Lotus",
    "price": 1.8,
    "date": "2025-08-09",
    "category": "uncategorized"
  },
  {
    "name": "Test Items",
    "brand": "Test",
    "supermarket": "Village Grocer",
    "price": 99.99,
    "category": "uncategorized",
    "date": "2025-08-09",
    "priceHistory": [
      {
        "price": 69.69,
        "date": "2025-08-09"
      }
    ]
  },
  {
    "name": "Test Items",
    "brand": "Testing2",
    "supermarket": "Jaya Grocer",
    "price": 1.29,
    "category": "uncategorized",
    "date": "2025-08-13",
    "priceHistory": [
      {
        "price": 29.99,
        "date": "2025-08-09"
      },
      {
        "price": 69.99,
        "date": "2025-08-09"
      },
      {
        "price": 60.69,
        "date": "2025-08-09"
      },
      {
        "price": 67.67,
        "date": "2025-08-09"
      },
      {
        "price": 29.99,
        "date": "2025-08-09"
      },
      {
        "price": 69.99,
        "date": "2025-08-08"
      },
      {
        "price": 71.99,
        "date": "2025-08-08"
      },
      {
        "price": 72.99,
        "date": "2025-08-08"
      },
      {
        "price": 70.99,
        "date": "2024-11-15"
      },
      {
        "price": 60.96,
        "date": "2023-07-18"
      }
    ]
  },
  {
    "name": "Test Items",
    "brand": "Testing",
    "supermarket": "99 Speedmart",
    "price": 300,
    "category": "uncategorized",
    "date": "2025-08-09",
    "priceHistory": [
      {
        "price": 29.99,
        "date": "2025-08-09"
      }
    ]
  },
  {
    "name": "Nathaniel Klansman",
    "brand": "Nathaniel",
    "supermarket": "Texas",
    "price": 99.99,
    "date": "2025-08-09",
    "category": "uncategorized",
    "priceHistory": []
  },
  {
    "name": "Eggs x30",
    "brand": "QL Grade A",
    "supermarket": "Jaya Grocer",
    "price": 12.6,
    "category": "uncategorized",
    "date": "2025-08-13"
  },
  {
    "name": "Eggs x30",
    "brand": "MS Classic Grade C",
    "supermarket": "Jaya Grocer",
    "price": 10.9,
    "category": "uncategorized",
    "date": "2025-08-13"
  },
  {
    "name": "Cat Food (Wet)",
    "brand": "ProDiet 85g",
    "supermarket": "Village Grocer",
    "price": 1.9,
    "date": "2025-08-13",
    "category": "uncategorized"
  },
  {
    "name": "Carrot",
    "brand": "Aus 800g",
    "supermarket": "Village Grocer",
    "price": 3.4,
    "date": "2025-08-13",
    "category": "produce"
  },
  {
    "name": "Beef",
    "brand": "AUS Grass Fed Ribeye per kg",
    "supermarket": "Village Grocer",
    "price": 159.9,
    "date": "2025-08-13",
    "category": "meat"
  },
  {
    "name": "Rice",
    "brand": "Mewah Nusantara White 5kg",
    "supermarket": "Village Grocer",
    "price": 21.2,
    "date": "2025-08-13",
    "category": "uncategorized"
  },
  {
    "name": "Eggs x15",
    "brand": "Savoir Omega Lutein ",
    "supermarket": "Village Grocer",
    "price": 8.9,
    "date": "2025-08-13",
    "category": "uncategorized"
  },
  {
    "name": "Baking Chocolate",
    "brand": "Callebaut W2 White 400g",
    "supermarket": "Village Grocer",
    "price": 67.4,
    "date": "2025-08-13",
    "category": "snacks"
  },
  {
    "name": "Butter",
    "brand": "Emborg Salted/Unsalted 200g",
    "supermarket": "Village Grocer",
    "price": 14.95,
    "date": "2025-08-13",
    "category": "dairy"
  },
  {
    "name": "Cooking Cream",
    "brand": "Anchor UHT 200mL",
    "supermarket": "Village Grocer",
    "price": 8.1,
    "date": "2025-08-13",
    "category": "dairy"
  },
  {
    "name": "Cream Cheese",
    "brand": "Tatura 250g",
    "supermarket": "Village Grocer",
    "price": 11.8,
    "date": "2025-08-13",
    "category": "dairy"
  },
  {
    "name": "Rice",
    "brand": "Mewah Thai White 5kg",
    "supermarket": "Village Grocer",
    "price": 23.7,
    "category": "uncategorized",
    "date": "2025-08-13"
  },
  {
    "name": "Baking Chocolate",
    "brand": "Callebaut 823 Milk Chocolate 400g",
    "supermarket": "Village Grocer",
    "price": 71.85,
    "category": "snacks",
    "date": "2025-08-13"
  },
  {
    "name": "Baking Chocolate",
    "brand": "Callebaut 811 Dark Chocolate 400g",
    "supermarket": "Village Grocer",
    "price": 78,
    "category": "snacks",
    "date": "2025-08-13"
  },
  {
    "name": "Baking Chocolate",
    "brand": "Callebaut 70-30-38",
    "supermarket": "Village Grocer",
    "price": 83.75,
    "category": "snacks",
    "date": "2025-08-13"
  },
  {
    "name": "Butter",
    "brand": "Emborg Cook & Bake",
    "supermarket": "Village Grocer",
    "price": 7.7,
    "category": "dairy",
    "date": "2025-08-13"
  },
  {
    "name": "Butter",
    "brand": "Tatura Salted/Unsalted 250g",
    "supermarket": "Village Grocer",
    "price": 18.25,
    "category": "dairy",
    "date": "2025-08-13"
  },
  {
    "name": "Butter",
    "brand": "SCS Salted/Unsalted 225g",
    "supermarket": "Village Grocer",
    "price": 18.5,
    "category": "dairy",
    "date": "2025-08-13"
  },
  {
    "name": "Cream Cheese",
    "brand": "Tatura 500g",
    "supermarket": "Village Grocer",
    "price": 21.6,
    "category": "dairy",
    "date": "2025-08-13"
  },
  {
    "name": "Cream Cheese",
    "brand": "Tatura 1kg",
    "supermarket": "Village Grocer",
    "price": 41.8,
    "category": "dairy",
    "date": "2025-08-13"
  },
  {
    "name": "Cooking/Frying Oil 1L",
    "brand": "Knife Brand",
    "supermarket": "Village Grocer",
    "price": 8.5,
    "date": "2025-08-13",
    "category": "condiments"
  },
  {
    "name": "Vanilla Flavouring",
    "brand": "Star Brand",
    "supermarket": "Village Grocer",
    "price": 3,
    "category": "uncategorized",
    "date": "2025-08-13"
  },
  {
    "name": "Oreo (Regular)",
    "brand": "Oreo",
    "supermarket": "Village Grocer",
    "price": 3,
    "date": "2025-08-13",
    "category": "uncategorized"
  },
  {
    "name": "Oreo 3x9",
    "brand": "Oreo",
    "supermarket": "Village Grocer",
    "price": 7.65,
    "category": "uncategorized",
    "date": "2025-08-13"
  },
  {
    "name": "Hup Seng Cream Crackers",
    "brand": "Hup Seng",
    "supermarket": "Village Grocer",
    "price": 5.65,
    "category": "dairy",
    "date": "2025-08-13"
  },
  {
    "name": "Butter",
    "brand": "Anchor Salted/Unsalted 250g",
    "supermarket": "Village Grocer",
    "price": 16.15,
    "category": "dairy",
    "date": "2025-08-13"
  },
  {
    "name": "Butter",
    "brand": "Farmcows Spread 200g",
    "supermarket": "Village Grocer",
    "price": 6,
    "category": "dairy",
    "date": "2025-08-13"
  },
  {
    "name": "Butter",
    "brand": "Buttercup 250g",
    "supermarket": "Village Grocer",
    "price": 8.5,
    "category": "dairy",
    "date": "2025-08-13"
  },
  {
    "name": "Cooking/Frying Oil 1L",
    "brand": "Buruh",
    "supermarket": "Village Grocer",
    "price": 6.9,
    "category": "condiments",
    "date": "2025-08-13"
  }
]